datasonar/__init__.py
datasonar/builders/SonarExecutorBuilder.py
datasonar/builders/__init__.py
datasonar/enums/FileFormat.py
datasonar/enums/__init__.py
datasonar/models/__init__.py
datasonar/models/data_files/DataFile.py
datasonar/models/data_files/__init__.py
datasonar/models/executors/SonarExecutor.py
datasonar/models/executors/__init__.py
datasonar/models/sonars/DateSonar.py
datasonar/models/sonars/ValueSubstitutionSonar.py
datasonar/models/sonars/__init__.py
datasonar/models/sonars/abstractions/BaseSonar.py
datasonar/models/sonars/abstractions/__init__.py
datasonar/services/__init__.py
datasonar/services/IO/DataFileService.py
datasonar/services/IO/__init__.py
datasonar-1.0.1.dist-info/LICENSE
datasonar-1.0.1.dist-info/METADATA
datasonar-1.0.1.dist-info/WHEEL
datasonar-1.0.1.dist-info/top_level.txt
datasonar-1.0.1.dist-info/RECORD
