Metadata-Version: 2.1
Name: datasonar
Version: 1.0.1
Home-page: https://github.com/Neyzv/DataSonar
Author: Neyzu
License-File: LICENSE
Requires-Dist: pandas
Requires-Dist: dask[dataframe]
Requires-Dist: pyarrow
